[
  {
    "Id": 1,
    "Name": "zzz",
    "Phone": "1123123",
    "Address": "asdf",
    "Email": "zzz@gmail.com",
    "Password": "123"
  },
  {
    "Id": 2,
    "Name": "ssss",
    "Phone": "asas",
    "Address": "sasas",
    "Email": "sss",
    "Password": "123"
  },
  {
    "Id": 3,
    "Name": "ddd",
    "Phone": "1232",
    "Address": "sdads",
    "Email": "ddd@gmail.com",
    "Password": "123"
  },
  {
    "Id": 4,
    "Name": "fff",
    "Phone": "234",
    "Address": "sddfs",
    "Email": "fff@gmail.com",
    "Password": "123"
  },
  {
    "Id": 5,
    "Name": "rrr",
    "Phone": "324324",
    "Address": "sadasdd",
    "Email": "rrr@gail.com",
    "Password": "123"
  },
  {
    "Id": 6,
    "Name": "ahmed",
    "Phone": "0110351045",
    "Address": "sid bishr",
    "Email": "ahmedSafwat@gmail.com",
    "Password": "123"
  },
  {
    "Id": 7,
    "Name": "ahmed",
    "Phone": "998",
    "Address": "hhsjds",
    "Email": "nnn@gmail.com",
    "Password": "123"
  },
  {
    "Id": 8,
    "Name": "Safwat",
    "Phone": "01233434545",
    "Address": "Alex",
    "Email": "Safwat@gmail.com",
    "Password": "123"
  },
  {
    "Id": 9,
    "Name": "1",
    "Phone": "1",
    "Address": "1",
    "Email": "1",
    "Password": "1"
  },
  {
    "Id": 10,
    "Name": "1",
    "Phone": "5",
    "Address": "5",
    "Email": "5",
    "Password": "5"
  },
  {
    "Id": 11,
    "Name": "99999",
    "Phone": "9999999999999",
    "Address": "99999999999",
    "Email": "9999999999",
    "Password": "9"
  },
  {
    "Id": 12,
    "Name": "5555555555",
    "Phone": "555555555555",
    "Address": "5555555555555555555",
    "Email": "555555555555555",
    "Password": "555555555555555"
  },
  {
    "Id": 13,
    "Name": "njdzbmdklbdf",
    "Phone": "55f55f5f5f",
    "Address": "hhhhhhhhhhhhhhhhhhhhhhhh",
    "Email": "kllllllll",
    "Password": "fv55f5f5f"
  },
  {
    "Id": 14,
    "Name": "258741265",
    "Phone": "5487451",
    "Address": "54678jhgfdhsg",
    "Email": "2569478964523",
    "Password": "548764521"
  },
  {
    "Id": 15,
    "Name": "1kkjkjjhgffddf",
    "Phone": "l;kfgdsdrftgjhkl;'",
    "Address": "548645312lkjhgf",
    "Email": "jhjgffdfgghghghhhhhhh",
    "Password": "kjhgfdswertyhjukilop"
  },
  {
    "Id": 16,
    "Name": "ss",
    "Phone": "ss",
    "Address": "ss",
    "Email": "ss",
    "Password": "ss"
  },
  {
    "Id": 17,
    "Name": "aa",
    "Phone": "aa",
    "Address": "",
    "Email": "aa",
    "Password": "aa"
  },
  {
    "Id": 18,
    "Name": "xx",
    "Phone": "xx",
    "Address": "xx",
    "Email": "xx",
    "Password": "xx"
  },
  {
    "Id": 19,
    "Name": "dddd",
    "Phone": "dddd",
    "Address": "dddd",
    "Email": "dddd",
    "Password": "dddd"
  }
]